ourlattice/__init__.py
ourlattice/accessors/__init__.py
ourlattice/accessors/facet.py
ourlattice/accessors/lattice.py
ourlattice/accessors/polytope.py
ourlattice/utils/__init__.py
ourlattice/utils/storages/__init__.py
ourlattice/utils/storages/local_storage.py
ourlattice/utils/storages/storage.py
tests/__init__.py
tests/accessors/__init__.py
tests/accessors/test_polytope.py
ourlattice-0.0.3.dist-info/LICENSE
ourlattice-0.0.3.dist-info/METADATA
ourlattice-0.0.3.dist-info/WHEEL
ourlattice-0.0.3.dist-info/top_level.txt
ourlattice-0.0.3.dist-info/RECORD
